fluentogram/__init__.py
fluentogram/__main__.py
fluentogram/exceptions.py
fluentogram/runner.py
fluentogram/translator.py
fluentogram/translator_hub.py
fluentogram/cli/__init__.py
fluentogram/cli/main.py
fluentogram/nats/__init__.py
fluentogram/nats/hub.py
fluentogram/nats/mock.py
fluentogram/nats/storage.py
fluentogram/src/impl/transator_hubs/__init__.py
fluentogram/storage/__init__.py
fluentogram/storage/base.py
fluentogram/storage/file.py
fluentogram/storage/memory.py
fluentogram/stub_generator/__init__.py
fluentogram/stub_generator/generator.py
fluentogram/stub_generator/parser.py
fluentogram/stub_generator/stubs.py
fluentogram/stub_generator/templates.py
fluentogram/stub_generator/tree.py
fluentogram/transformers/__init__.py
fluentogram/transformers/base.py
fluentogram/transformers/datetime.py
fluentogram/transformers/money.py
fluentogram-1.2.0.dist-info/licenses/LICENSE
fluentogram-1.2.0.dist-info/METADATA
fluentogram-1.2.0.dist-info/WHEEL
fluentogram-1.2.0.dist-info/entry_points.txt
fluentogram-1.2.0.dist-info/top_level.txt
fluentogram-1.2.0.dist-info/RECORD
