Metadata-Version: 2.4
Name: fluentogram
Version: 1.2.0
Summary: Fluentogram is easy way to use i18n (Fluent) mechanism in any python app.
Author: Aleks
License-Expression: MIT
Project-URL: Repository, https://github.com/Arustinal/fluentogram
Requires-Python: >=3.9
License-File: LICENSE
Requires-Dist: fluent-compiler~=1.1
Provides-Extra: stubs
Requires-Dist: jinja2<4,>=3.1.0; extra == "stubs"
Provides-Extra: cli
Requires-Dist: fluentogram[stubs]; extra == "cli"
Requires-Dist: watchdog>=3.0.0; extra == "cli"
Provides-Extra: aiogram
Requires-Dist: aiogram~=3.20.0; extra == "aiogram"
Provides-Extra: nats
Requires-Dist: nats-py~=2.10.0; extra == "nats"
Provides-Extra: dev
Requires-Dist: fluentogram[aiogram,cli,nats]; extra == "dev"
Requires-Dist: ruff~=0.11.2; extra == "dev"
Requires-Dist: pytest~=8.4.1; extra == "dev"
Requires-Dist: pre-commit~=4.2.0; extra == "dev"
Requires-Dist: detect-secrets~=1.5.0; extra == "dev"
Requires-Dist: pytest-asyncio~=1.0.0; extra == "dev"
Dynamic: license-file
